Workbook
Name Category: #REF!
Name Category: #REF!
Name Change: #REF!
Name Change: #REF!
Name Chiến_lược: '3. Risk mapping'!#REF!
Name d: #REF!
Name Definition: #REF!
Name Definition: #REF!
Name e: #REF!
Name Impact: #REF!
Name Impact: #REF!
Name Likelihood: #REF!
Name Likelihood: #REF!
Name s: #REF!
Name sdfs: #REF!
Name Status: #REF!
Name Status: #REF!
Name SubCategory: #REF!
Name SubCategory: #REF!

Sheet 0. Introduction
A1: Company Name
A2: Annual risk assessment and IA planning
A3: Year:
A5: Introduction
A7: 1. Audit universe | B7: List of auditable units at "Company"
A11: 2. Risk sheet | B11: List of risks identified and assessed based on defined criteria. The assessment is performed for residual risk (the risk rating after consideration of controls mitigating risks).
A17: 3. Risk mapping | B17: Prioritized risk's rating (residual risk rating) at 2. Risk sheet is linked to auditable unit at 1. Audit universe
A22: 4. Location mapping | B22: Risk rating at processes is linked to locations
A29: 5. IA plan | B29: IA plan is developed based on input from 3. Risk mapping and 4. Location mapping

Sheet 1. Audit universe
A1: ='0. Introduction'!A1 -> Company Name
A2: Annual risk assessment and IA planning
A3: ='0. Introduction'!A3 -> Year:
A5: Audit universe
A7: Function | B7: Head Quarter | C7: Hanoi | D7: Hai Phong | E7: HCM
A8: Corporate planning | B8: Corporate
B9: Planning
A10: Corporate management | B10: Legal
B11: Business management
A12: Finance & accounting | B12: Finance
B13: Accounting
A14: HR | B14: Employment Relation
B15: Recruitment
B16: Payroll
B17: Training & development
A18: IT | B18: IT System/Infrastructure
B19: IT Solutions/applications
A20: Business development & Customer service | C20: Business development | D20: Business development | E20: Business development
C21: Customer service | D21: Customer service | E21: Customer service
A22: Project cargoes | C22: Project cargoes | E22: Project cargoes
A23: Admin | C23: Hanoi | D23: HLC | E23: HCMC
C24: YLC, TTLC, TS, VSIP
A25: Warehouse | C25: YLC/Quang Minh | D25: HPH Container Depot | E25: MLC (Sony)
C26: TLC Bac Ninh | D26: HLC | E26: SLC/TBS
C27: VSIP Bac Ninh | D27: JX | E27: Kerry
C28: TTLC Hai Duong | D28: BTMV

Sheet 2. Risk sheet
A1: ='0. Introduction'!A1 -> Company Name | E1: Adequate | F1: 1
A2: Annual risk assessment and IA planning | E2: Inadequate | F2: 2
A3: ='0. Introduction'!A3 -> Year: | E3: Nonexistence | F3: 3
F4: 4
A5: Risk sheet | I5: Control design assessment
A7: No. | B7: Risk name | C7: Risk description | D7: Control | E7: Control assessment | F7: Residual risk | G7: IA focus | I7: Adequate | L7: Inadequate | N7: Nonexistence
A8: R01 | B8: Third party relationships | C8: Ineffective management oversight of contracted third party service providers’ performance and compliance. | E8: Nonexistence | F8: 3 | I8: The control processes and management's mitigating activities allow for effective management of the risk, thereby reducing the frequency and/or impact of the risk event occurring | L8: The control processes and management's mitigating activities allow for marginal management of the risk, there is minimal reduction in the frequency and/or severity of the risk event. Major gaps and deficiencies have been identified. | N8: There is no control processes and management's mitigating activities for the management of the risk. There is no reduction in the frequency and/or severity of the risk event.
A9: R02 | B9: Ineffective vendor selection process | C9: Failure to identify quality and cost effective third party suppliers | F9: 1
A10: R03 | B10: Customs compliance and duty reduction | C10: Inability to identify opportunities to eliminate customs duty throughout the supply chain. Misinterpretation of cross-border and customs legislation leads to overpaid duties and delays at the border. | E10: Inadequate | F10: 1 | I10: Residual risk rating
A11: R04 | B11: Planning and forecasting demands | C11: Failure to forecast clients’ demand leading to failure in capacity utilization | E11: Adequate | F11: 3
A12: R05 | B12: Delivery destination | C12: Failure to record and interpret correctly delivery address provided by client leading to higher transportation expense or failure to complete services. | F12: 2
A13: R06 | B13: Warehouse development | C13: Failure to equip and develop warehouse to meet specific requirements for particular type of good. | F13: 2
A14: R07 | B14: Physical control | C14: Failure to perform and manage the physical order fulfillment process of picking, packing goods in a manner consistent with customer expectations. | F14: 2
A15: R08 | B15: Insurance | C15: Insurance coverage fails to protect the Company from significant financial losses due to incidents and claims. | F15: 2
A16: R09 | B16: Transportation vehicle controls and maintenance | C16: Failure to provide physical protection and stewardship over transportation vehicles (trucks, container, etc.) | F16: 2
A17: R10 | B17: Goods management during transporting and storing process | C17: Failure to maintain quality and quantity of special goods (frozen food, fragile products, living animals, etc.) | F17: 2
A18: R11 | B18: Crisis Communication | C18: Failure to communicate the right message in an effective manner to recover and maintain business operations in the event of a crisis or disruption due to physical or natural circumstances. | F18: 2
A19: R12 | B19: Marketing | C19: The inability to articulate a message that communicates a consistent and compelling incentive for potential consumers and provides a return on investment to shareholders. | F19: 2
A20: R13 | B20: Sales and Pricing | C20: Inability to price and provide services to key target markets in order to achieve the Company's strategic and financial goals. | F20: 2
A21: R14 | B21: Customer Support / Management | C21: Failure to provide customer service to enable long-term customer loyalty. Includes ineffective response to customer needs, questions and concerns about the Company's products and/or services. | F21: 2
A22: R15 | B22: Fraud | C22: Potential illegal acts committed by Company employees to sneak illegal goods cross border that negatively impact the Company's reputation. | F22: 2
A23: R16 | B23: Contract | C23: Entering into contracts that are unfavorable to the Company; and the failure to comply with and monitor contract terms to protect the Company from financial losses. | F23: 2
... A43: R36 | B43: Chemical disaster | C43: Risk of disaster as fire, contamination, infestation (rodents, insects). | F43: 2

Sheet 3. Risk mapping
A1: ='0. Introduction'!A1 -> Company Name
A2: Annual risk assessment and IA planning
A3: ='0. Introduction'!A3 -> Year:
A5: Risk mapping
A7: Department | F7: Operation 1 | G7: Operation 2 | H7: … | I7: … | J7: Warehouse | K7: BD & CS | L7: Finance & accounting | M7: HR | N7: IT | O7: Corporate planning | P7: Corporate management | Q7: Admin
B8: No. | C8: Risk | D8: Risk description | E8: Rating
B9: ='2. Risk sheet'!A8 -> R01 | C9: ='2. Risk sheet'!B8 -> Third party relationships | D9: ='2. Risk sheet'!C8 -> Ineffective management oversight of contracted third party service providers’ performance and compliance. | E9: ='2. Risk sheet'!F8 -> 3
B10: ='2. Risk sheet'!A9 -> R02 | C10: ='2. Risk sheet'!B9 -> Ineffective vendor selection process | D10: ='2. Risk sheet'!C9 -> Failure to identify quality and cost effective third party suppliers | E10: ='2. Risk sheet'!F9 -> 1
B11: ='2. Risk sheet'!A10 -> R03 | C11: ='2. Risk sheet'!B10 -> Customs compliance and duty reduction | D11: ='2. Risk sheet'!C10 -> Inability to identify opportunities to eliminate customs duty throughout the supply chain. Misinterpretation of cross-border and customs legislation leads to overpaid duties and delays at the border. | E11: ='2. Risk sheet'!F10 -> 1
B12: ='2. Risk sheet'!A11 -> R04 | C12: ='2. Risk sheet'!B11 -> Planning and forecasting demands | D12: ='2. Risk sheet'!C11 -> Failure to forecast clients’ demand leading to failure in capacity utilization | E12: ='2. Risk sheet'!F11 -> 3
B13: ='2. Risk sheet'!A12 -> R05 | C13: ='2. Risk sheet'!B12 -> Delivery destination | D13: ='2. Risk sheet'!C12 -> Failure to record and interpret correctly delivery address provided by client leading to higher transportation expense or failure to complete services. | E13: ='2. Risk sheet'!F12 -> 2
B14: ='2. Risk sheet'!A13 -> R06 | C14: ='2. Risk sheet'!B13 -> Warehouse development | D14: ='2. Risk sheet'!C13 -> Failure to equip and develop warehouse to meet specific requirements for particular type of good. | E14: ='2. Risk sheet'!F13 -> 2
B15: ='2. Risk sheet'!A14 -> R07 | C15: ='2. Risk sheet'!B14 -> Physical control | D15: ='2. Risk sheet'!C14 -> Failure to perform and manage the physical order fulfillment process of picking, packing goods in a manner consistent with customer expectations. | E15: ='2. Risk sheet'!F14 -> 2
B16: ='2. Risk sheet'!A15 -> R08 | C16: ='2. Risk sheet'!B15 -> Insurance | D16: ='2. Risk sheet'!C15 -> Insurance coverage fails to protect the Company from significant financial losses due to incidents and claims. | E16: ='2. Risk sheet'!F15 -> 2
B17: ='2. Risk sheet'!A16 -> R09 | C17: ='2. Risk sheet'!B16 -> Transportation vehicle controls and maintenance | D17: ='2. Risk sheet'!C16 -> Failure to provide physical protection and stewardship over transportation vehicles (trucks, container, etc.) | E17: ='2. Risk sheet'!F16 -> 2
B18: ='2. Risk sheet'!A17 -> R10 | C18: ='2. Risk sheet'!B17 -> Goods management during transporting and storing process | D18: ='2. Risk sheet'!C17 -> Failure to maintain quality and quantity of special goods (frozen food, fragile products, living animals, etc.) | E18: ='2. Risk sheet'!F17 -> 2
B19: ='2. Risk sheet'!A18 -> R11 | C19: ='2. Risk sheet'!B18 -> Crisis Communication | D19: ='2. Risk sheet'!C18 -> Failure to communicate the right message in an effective manner to recover and maintain business operations in the event of a crisis or disruption due to physical or natural circumstances. | E19: ='2. Risk sheet'!F18 -> 2
B20: ='2. Risk sheet'!A19 -> R12 | C20: ='2. Risk sheet'!B19 -> Marketing | D20: ='2. Risk sheet'!C19 -> The inability to articulate a message that communicates a consistent and compelling incentive for potential consumers and provides a return on investment to shareholders. | E20: ='2. Risk sheet'!F19 -> 2
... B44: ='2. Risk sheet'!A43 -> R36 | C44: ='2. Risk sheet'!B43 -> Chemical disaster | D44: ='2. Risk sheet'!C43 -> Risk of disaster as fire, contamination, infestation (rodents, insects). | E44: ='2. Risk sheet'!F43 -> 2
A45: Risk score | F45: =SUM(F9:F44) -> 0 | G45: =SUM(G9:G44) -> 0 | H45: =SUM(H9:H44) -> 0 | I45: =SUM(I9:I44) -> 0 | J45: =SUM(J9:J44) -> 0 | K45: =SUM(K9:K44) -> 0 | L45: =SUM(L9:L44) -> 0 | M45: =SUM(M9:M44) -> 0 | ... Q45: =SUM(Q9:Q44) -> 0

Sheet 4. Location mapping
A1: ='0. Introduction'!A1 -> Company Name
A2: Annual risk assessment and IA planning
A3: ='0. Introduction'!A3 -> Year:
A5: Location mapping
A6: Department | B6: Risk assessment | C6: HQ | D6: HN | E6: HPH | F6: HCM
A8: Operation 1 | B8: ='3. Risk mapping'!F$45 -> 0 | D8: X | F8: X
A9: Operation 2 | B9: ='3. Risk mapping'!G$45 -> 0 | D9: X | F9: X
A10: … | B10: ='3. Risk mapping'!H$45 -> 0 | D10: X | F10: X
A11: … | B11: ='3. Risk mapping'!J$45 -> 0 | D11: X | E11: X | F11: X
A12: IT | B12: ='3. Risk mapping'!N$45 -> 0 | C12: X
B13: ='3. Risk mapping'!I$45 -> 0 | D13: X | E13: X | F13: X
A14: HR | B14: ='3. Risk mapping'!M$45 -> 0 | C14: X
A15: Finance & accounting | B15: ='3. Risk mapping'!L$45 -> 0 | C15: X
A16: BD & CS | B16: ='3. Risk mapping'!K$45 -> 0 | D16: X | E16: X | F16: X
A17: Corporate management | B17: ='3. Risk mapping'!P$45 -> 0 | C17: X
A18: Admin | B18: ='3. Risk mapping'!Q$45 -> 0 | D18: X | E18: X | F18: X
A19: Corporate planning | B19: ='3. Risk mapping'!O$45 -> 0 | C19: X

Sheet 5. IA plan
A1: ='0. Introduction'!A1 -> Company Name
A2: Annual risk assessment and IA planning
A3: ='0. Introduction'!A3 -> Year:
A5: IA plan
A7: No. | B7: Department | C7: Risk | D7: IA focus | E7: Location | F7: Required resource | G7: Timing
C27: Available resources
C28: 1. IAC's internal auditors for 20xx:
C29: - 01 Head of IAC (to be team leader) | D29: Full time
C30: - 01 Audit manager | D30: Full time
C31: - 01 Auditor (to be recruited in 2017) | D31: Full time
C32: 2. Guest auditors - if any (see table below) | D32: 05 weeks/each
C33: Department | D33: North | E33: South
C34: Warehouse
C35: Operation 1
C36: Operation 2
C37: …
C38: …
C39: BD & CS
C40: IT
C41: FA
C42: CM & CP
